LICENSE.txt
MANIFEST.in
README.md
setup.py
g2p_seq2seq/__init__.py
g2p_seq2seq/app.py
g2p_seq2seq/data_reader_old.py
g2p_seq2seq/g2p.py
g2p_seq2seq/g2p_cleaned.py
g2p_seq2seq/g2p_encoder.py
g2p_seq2seq/g2p_new.py
g2p_seq2seq/g2p_old.py
g2p_seq2seq/g2p_problem.py
g2p_seq2seq/g2p_trainer_utils.py
g2p_seq2seq/input_fn_builder_old.py
g2p_seq2seq/model_builder_old.py
g2p_seq2seq/params.py
g2p_seq2seq.egg-info/PKG-INFO
g2p_seq2seq.egg-info/SOURCES.txt
g2p_seq2seq.egg-info/dependency_links.txt
g2p_seq2seq.egg-info/entry_points.txt
g2p_seq2seq.egg-info/requires.txt
g2p_seq2seq.egg-info/top_level.txt