Metadata-Version: 1.1
Name: g2p-seq2seq
Version: 6.0.0a0
Summary: Grapheme to phoneme module based on Seq2Seq
Home-page: https://github.com/cmusphinx/g2p-seq2seq
Author: Nurtas Makhazhanov
Author-email: makhazhanovn@gmail.com
License: Apache Software License
Keywords: g2p seq2seq tensor2tensor rnnlm
Platform: UNKNOWN
Classifier: Development Status :: 3 - Alpha
Classifier: Intended Audience :: Developers
Classifier: Topic :: Software Development :: Build Tools
Classifier: License :: OSI Approved :: Apache Software License
Classifier: Programming Language :: Python :: 2.6
Classifier: Programming Language :: Python :: 2.7
Classifier: Programming Language :: Python :: 3.4
Classifier: Programming Language :: Python :: 3.5
